{
    "BITD.contacts_adelaide_phroaig": "adelaide phroaig",
    "BITD.contacts_adelaide_phroaig_description": "a noble",
    "BITD.contacts_adelaide_phroaig_long_description": "Perhaps a source for scores among the elite?",
    "BITD.contacts_adikin": "adikin",
    "BITD.contacts_adikin_description": "an occultist",
    "BITD.contacts_adikin_long_description": "Perhaps a medium to the dark powers?",
    "BITD.contacts_amancio": "amancio",
    "BITD.contacts_amancio_description": "a deal broker",
    "BITD.contacts_amancio_long_description": "Perhaps a well-connected underworld figure, famous for their neutrality?",
    "BITD.contacts_anis": "anis",
    "BITD.contacts_anis_description": "a spirit warden",
    "BITD.contacts_anis_long_description": "",
    "BITD.contacts_anya": "anya",
    "BITD.contacts_anya_description": "a dillettante",
    "BITD.contacts_anya_long_description": "Perhaps a well-connected socialite?",
    "BITD.contacts_augus": "augus",
    "BITD.contacts_augus_description": "a master architect",
    "BITD.contacts_augus_long_description": "Perhaps a good source for building schematics and historical details, or perhaps a rival who designs a security measures?",
    "BITD.contacts_badger": "badger",
    "BITD.contacts_badger_description": "a brilliant inventor",
    "BITD.contacts_badger_long_description": "",
    "BITD.contacts_bazso_baz": "bazso baz",
    "BITD.contacts_bazso_baz_description": "a gang leader",
    "BITD.contacts_bazso_baz_long_description": "Perhaps a paramour pursuing your affections, or perhaps a former lover, now scorned?",
    "BITD.contacts_bennett": "bennett",
    "BITD.contacts_bennett_description": "an astronomer",
    "BITD.contacts_bennett_long_description": "Perhaps he's seen them in the stars, or the sea?",
    "BITD.contacts_bryl": "bryl",
    "BITD.contacts_bryl_description": "a drug dealer",
    "BITD.contacts_bryl_long_description": "Perhaps a reliable underworld contact, or perhaps an old partner with a grudge?",
    "BITD.contacts_casta": "casta",
    "BITD.contacts_casta_description": "a bounty hunter",
    "BITD.contacts_casta_long_description": "Perhaps a mentor who trained you in the deadly arts, or vice versa?",
    "BITD.contacts_celene": "celene",
    "BITD.contacts_celene_description": "a sentinel",
    "BITD.contacts_celene_long_description": "Celene is a guardian; a protector. Who does she watch over?",
    "BITD.contacts_chael": "chael",
    "BITD.contacts_chael_description": "a vicious thug",
    "BITD.contacts_chael_long_description": "Perhaps a member of a gang that you were in before the current crew, or an independent operator who's been in your way before?",
    "BITD.contacts_conway": "conway",
    "BITD.contacts_conway_description": "a Bluecoat",
    "BITD.contacts_conway_long_description": "Perhaps an informant within the City Watch?",
    "BITD.contacts_darmot": "darmot",
    "BITD.contacts_darmot_description": "a Bluecoat",
    "BITD.contacts_darmot_long_description": "Perhaps a savvy officer that's busted you many times, or perhaps an old friend who turned to the law instead of crime?",
    "BITD.contacts_decker": "decker",
    "BITD.contacts_decker_description": "an anarchist",
    "BITD.contacts_decker_long_description": "Perhaps a client in need of the illegal tools of the revolution?",
    "BITD.contacts_dowler": "dowler",
    "BITD.contacts_dowler_description": "an explorer",
    "BITD.contacts_dowler_long_description": "Perhaps one of the rare deathlands scavengers that survived his sentence?",
    "BITD.contacts_eckerd": "eckerd",
    "BITD.contacts_eckerd_description": "a corpse thief",
    "BITD.contacts_eckerd_long_description": "Perhaps a good source of \"raw materials\"?",
    "BITD.contacts_elynn": "elynn",
    "BITD.contacts_elynn_description": "a dock worker",
    "BITD.contacts_elynn_long_description": "Perhaps a friend who can help with the infernal paperwork of the Empire?",
    "BITD.contacts_esme": "esme",
    "BITD.contacts_esme_description": "a tavern owner",
    "BITD.contacts_esme_long_description": "Perhaps a good source of news and gossip?",
    "BITD.contacts_exeter": "exeter",
    "BITD.contacts_exeter_description": "a Spirit Warden",
    "BITD.contacts_exeter_long_description": "Perhaps a double-agent informant for you?",
    "BITD.contacts_fitz": "fitz",
    "BITD.contacts_fitz_description": "a collector",
    "BITD.contacts_fitz_long_description": "Perhaps an afficionado of strange artifacts?",
    "BITD.contacts_flint": "flint",
    "BITD.contacts_flint_description": "a spirit trafficker",
    "BITD.contacts_flint_long_description": "Perhaps a good source for unusual arcane supplies, or perhaps a rival in the occult world of Duskwall?",
    "BITD.contacts_frake": "frake",
    "BITD.contacts_frake_description": "a locksmith",
    "BITD.contacts_frake_long_description": "Perhaps an expert that you go to for consultations, or perhaps a master who creates locks to defeat you?",
    "BITD.contacts_gagan": "gagan",
    "BITD.contacts_gagan_description": "an academic",
    "BITD.contacts_gagan_long_description": "Perhaps a scholar reluctantly answering the dark calling?",
    "BITD.contacts_grace": "grace",
    "BITD.contacts_grace_description": "an extortionist",
    "BITD.contacts_grace_long_description": "Perhaps a former partner in thuggery, or a competitor on the scene?",
    "BITD.contacts_harker": "harker",
    "BITD.contacts_harker_description": "a jail bird",
    "BITD.contacts_harker_long_description": "Perhaps a friend who you helped when you were in prison, or perhaps an enemy who hurt you when you served your time?",
    "BITD.contacts_hoxley": "hoxley",
    "BITD.contacts_hoxley_description": "a smuggler",
    "BITD.contacts_hoxley_long_description": "Perhaps a friend of powerful ship captains?",
    "BITD.contacts_hutchins": "hutchins",
    "BITD.contacts_hutchins_description": "an antiquarian",
    "BITD.contacts_hutchins_long_description": "Perhaps a collector turned acolyte?",
    "BITD.contacts_irimina": "irimina",
    "BITD.contacts_irimina_description": "a vicious noble",
    "BITD.contacts_irimina_long_description": "Perhaps a potential patron for your crew?",
    "BITD.contacts_jennah": "jennah",
    "BITD.contacts_jennah_description": "a servant",
    "BITD.contacts_jennah_long_description": "Perhaps a good source for gossip among the upper class?",
    "BITD.contacts_jeren": "jeren",
    "BITD.contacts_jeren_description": "a Bluecoat archivist",
    "BITD.contacts_jeren_long_description": "Perhaps a double-agent within the City Watch, or perhaps an overly curious officer, interested in your crimes?",
    "BITD.contacts_jul": "jul",
    "BITD.contacts_jul_description": "a blood dealer",
    "BITD.contacts_jul_long_description": "What other strange clients do they have?",
    "BITD.contacts_karlos": "karlos",
    "BITD.contacts_karlos_description": "a bounty hunter",
    "BITD.contacts_karlos_long_description": "Perhaps a source for off-book government \"wet work\"",
    "BITD.contacts_keller": "keller",
    "BITD.contacts_keller_description": "a blacksmith",
    "BITD.contacts_keller_long_description": "Perhaps a source for armaments?",
    "BITD.contacts_klyra": "klyra",
    "BITD.contacts_klyra_description": "a tavern owner",
    "BITD.contacts_klyra_long_description": "Perhaps a good source for gossip?",
    "BITD.contacts_laroze": "laroze",
    "BITD.contacts_laroze_description": "a Bluecoat",
    "BITD.contacts_laroze_long_description": "Perhaps an informant within the City Watch?",
    "BITD.contacts_lutes": "lutes",
    "BITD.contacts_lutes_description": "a tavern owner",
    "BITD.contacts_lutes_long_description": "Perhaps a good source of news and gossip?",
    "BITD.contacts_lydra": "lydra",
    "BITD.contacts_lydra_description": "a deal broker",
    "BITD.contacts_lydra_long_description": "Perhaps known for her vicious retribution on those who don't hold up to their end?",
    "BITD.contacts_malista": "malista",
    "BITD.contacts_malista_description": "a priestess",
    "BITD.contacts_malista_long_description": "To what forgotten god does Malista give her service?",
    "BITD.contacts_mara": "mara",
    "BITD.contacts_mara_description": "a chief inspector",
    "BITD.contacts_mara_long_description": "",
    "BITD.contacts_marlane": "marlane",
    "BITD.contacts_marlane_description": "a pugilist",
    "BITD.contacts_marlane_long_description": "Perhaps a pit fighter down at the docks, or a boxing coach who trained you?",
    "BITD.contacts_marlo": "marlo",
    "BITD.contacts_marlo_description": "a gang boss",
    "BITD.contacts_marlo_long_description": "Perhaps a good partner with a gang of tough thugs?",
    "BITD.contacts_mateas_kline": "mateas kline",
    "BITD.contacts_mateas_kline_description": "a noble",
    "BITD.contacts_mateas_kline_long_description": "Perhaps he seeks to bring his family into the fold?",
    "BITD.contacts_meg": "meg",
    "BITD.contacts_meg_description": "a pit-fighter",
    "BITD.contacts_meg_long_description": "Perhaps a trainer, or perhaps a fellow extortion artist?",
    "BITD.contacts_melvir": "melvir",
    "BITD.contacts_melvir_description": "a physicker",
    "BITD.contacts_melvir_long_description": "Perhaps an old friend who's patched you up many times, or someone to whom you've sent too many victims?",
    "BITD.contacts_mercy": "mercy",
    "BITD.contacts_mercy_description": "a cold killer",
    "BITD.contacts_mercy_long_description": "Perhaps an assassin for hire, or a particularly deadly underworld scoundrel?",
    "BITD.contacts_moriya": "moriya",
    "BITD.contacts_moriya_description": "a spirit tracker",
    "BITD.contacts_moriya_long_description": "Perhaps she collects spirits for sacrifice?",
    "BITD.contacts_nyelle": "nyelle",
    "BITD.contacts_nyelle_description": "a spirit trafficker",
    "BITD.contacts_nyelle_long_description": "Perhaps a supplier for the strangest of cargo?",
    "BITD.contacts_nyryx": "nyryx",
    "BITD.contacts_nyryx_description": "a prostitute",
    "BITD.contacts_nyryx_long_description": "Perhaps an informant to spark potential marks, or perhaps a rival manipulator?",
    "BITD.contacts_petra": "petra",
    "BITD.contacts_petra_description": "a city clerk",
    "BITD.contacts_petra_long_description": "Perhaps a good source of information?",
    "BITD.contacts_quellyn": "quellyn",
    "BITD.contacts_quellyn_description": "a witch",
    "BITD.contacts_quellyn_long_description": "Perhaps a knowledgeable healer and seer, or perhaps a student of yours who left over bad blood?",
    "BITD.contacts_remira": "remira",
    "BITD.contacts_remira_description": "a reluctant Lampblack",
    "BITD.contacts_remira_long_description": "",
    "BITD.contacts_rigney": "rigney",
    "BITD.contacts_rigney_description": "a tavern owner",
    "BITD.contacts_rigney_long_description": "Perhaps a good source of news and gossip?",
    "BITD.contacts_riven": "riven",
    "BITD.contacts_riven_description": "a chemist",
    "BITD.contacts_riven_long_description": "Perhaps a good source of medicines for recovery?",
    "BITD.contacts_rolan": "rolan",
    "BITD.contacts_rolan_description": "a drug dealer",
    "BITD.contacts_rolan_long_description": "Perhaps a client with strong underworld ties?",
    "BITD.contacts_rolan_wott": "rolan wott",
    "BITD.contacts_rolan_wott_description": "a magistrate",
    "BITD.contacts_rolan_wott_long_description": "Perhaps with a feckless son in Doskvol academy, always in need of rescuing?",
    "BITD.contacts_roslyn_kellis": "roslyn kellis",
    "BITD.contacts_roslyn_kellis_description": "a noble",
    "BITD.contacts_roslyn_kellis_long_description": "Perhaps an old friend and confidant, or perhaps one of the victims of your espionage, bent on revenge?",
    "BITD.contacts_salia": "salia",
    "BITD.contacts_salia_description": "an information broker",
    "BITD.contacts_salia_long_description": "Perhaps a reliable contact for underworld jobs, or perhaps a former partner who sold you out?",
    "BITD.contacts_sawtooth": "sawtooth",
    "BITD.contacts_sawtooth_description": "a physicker",
    "BITD.contacts_sawtooth_long_description": "Perhaps a buddy from the war, or perhaps a butcher who botched your treatment?",
    "BITD.contacts_scurlock": "scurlock",
    "BITD.contacts_scurlock_description": "a vampire",
    "BITD.contacts_scurlock_long_description": "Perhaps a mentor, or perhaps a deadly rival?",
    "BITD.contacts_sera": "sera",
    "BITD.contacts_sera_description": "an arms dealer",
    "BITD.contacts_sera_long_description": "Perhaps a supplier with military access?",
    "BITD.contacts_setarra": "setarra",
    "BITD.contacts_setarra_description": "Perhaps your partner in a dark endeavour, or perhaps an entity you once controlled, seeking vengeance?",
    "BITD.contacts_setarra_long_description": "",
    "BITD.contacts_sevoy": "sevoy",
    "BITD.contacts_sevoy_description": "a merchant lord",
    "BITD.contacts_sevoy_long_description": "Perhaps a connection to clients with deep pockets?",
    "BITD.contacts_soren": "soren",
    "BITD.contacts_soren_description": "a restless ghost",
    "BITD.contacts_soren_long_description": "",
    "BITD.contacts_stazia": "stazia",
    "BITD.contacts_stazia_description": "an apothecary",
    "BITD.contacts_stazia_long_description": "Perhaps a former scoundrel turned to legitimate alchemical business, or perhaps the other way around?",
    "BITD.contacts_steiner": "steiner",
    "BITD.contacts_steiner_description": "an assassin",
    "BITD.contacts_steiner_long_description": "Perhaps one of your competitors, or a former partner before you joined the crew?",
    "BITD.contacts_telda": "telda",
    "BITD.contacts_telda_description": "a beggar",
    "BITD.contacts_telda_long_description": "Perhaps a mentor who taught you your skills, or perhaps a rival sneak-thief?",
    "BITD.contacts_tomas": "tomas",
    "BITD.contacts_tomas_description": "a physicker",
    "BITD.contacts_tomas_long_description": "Perhaps a former thug turned doctor?",
    "BITD.contacts_trev": "trev",
    "BITD.contacts_trev_description": "a gang boss",
    "BITD.contacts_trev_long_description": "Perhaps a gang that helped your crew get started?",
    "BITD.contacts_twelves": "twelves",
    "BITD.contacts_twelves_description": "a leviathan hunter",
    "BITD.contacts_twelves_long_description": "",
    "BITD.contacts_veldren": "veldren",
    "BITD.contacts_veldren_description": "a psychonaut",
    "BITD.contacts_veldren_long_description": "Perhaps an addict to poisoned to ever return to lucid thought, or perhaps an explorer of psychedelic realms beyond mere mortal experience?",
    "BITD.contacts_veleris": "veleris",
    "BITD.contacts_veleris_description": "a spy",
    "BITD.contacts_veleris_long_description": "Who does Veleris give his information to?",
    "BITD.contacts_walker": "walker",
    "BITD.contacts_walker_description": "a ward boss",
    "BITD.contacts_walker_long_description": "Perhaps an employer who often needs violent work?"
}